ptiistild/__init__.py
ptiistild/_version.py
ptiistild/ptiistild.py
ptiistild-1.0.11.dist-info/licenses/LICENSE
ptiistild-1.0.11.dist-info/METADATA
ptiistild-1.0.11.dist-info/WHEEL
ptiistild-1.0.11.dist-info/entry_points.txt
ptiistild-1.0.11.dist-info/top_level.txt
ptiistild-1.0.11.dist-info/RECORD
