Metadata-Version: 2.4
Name: ptiistild
Version: 1.0.11
Summary: IIS Tilde Enumeration Tool
Home-page: https://www.penterep.com/
Author: Penterep
Author-email: info@penterep.com
License: GPLv3+
Project-URL: homepage, https://www.penterep.com/
Project-URL: repository, https://github.com/penterep/ptiistild
Project-URL: tracker, https://github.com/penterep/ptiistild/issues
Project-URL: changelog, https://github.com/penterep/ptiistild/blob/main/CHANGELOG.md
Classifier: Programming Language :: Python :: 3
Classifier: Programming Language :: Python :: Implementation :: CPython
Classifier: Environment :: Console
Classifier: Topic :: Security
Classifier: License :: OSI Approved :: GNU General Public License v3 or later (GPLv3+)
Requires-Python: >=3.9
License-File: LICENSE
Requires-Dist: ptlibs<2,>=1
Requires-Dist: validators
Dynamic: author
Dynamic: author-email
Dynamic: classifier
Dynamic: description
Dynamic: description-content-type
Dynamic: home-page
Dynamic: license
Dynamic: license-file
Dynamic: project-url
Dynamic: requires-dist
Dynamic: requires-python
Dynamic: summary
